dpfm_model_runners/__init__.py
dpfm_model_runners/atlas_runner.py
dpfm_model_runners/autoclass_runner.py
dpfm_model_runners/conch_runner.py
dpfm_model_runners/exaonepath_runner.py
dpfm_model_runners/google_runner.py
dpfm_model_runners/model_factory.py
dpfm_model_runners/provgigapath_runner.py
dpfm_model_runners/virchow2_runner.py
dpfm_model_runners/data/macenko_target.png
dpfm_factory-0.13.7.dist-info/METADATA
dpfm_factory-0.13.7.dist-info/WHEEL
dpfm_factory-0.13.7.dist-info/dependency_links.txt
dpfm_factory-0.13.7.dist-info/top_level.txt
dpfm_factory-0.13.7.dist-info/RECORD
