Metadata-Version: 2.4
Name: dpfm_factory
Version: 0.13.7
Summary: Helper scripts for digital pathology foundation models
Author: Steven N. Hart
Author-email: Hart.Steven@Mayo.edu
Requires-Dist: httpx
Requires-Dist: huggingface_hub>=0.26.2
Requires-Dist: importlib_resources
Requires-Dist: nest_asyncio
Requires-Dist: python-dotenv
Requires-Dist: tensorflow>=2.17.1
Requires-Dist: timm
Requires-Dist: tqdm
Requires-Dist: torch
Requires-Dist: torchvision
Requires-Dist: torchstain>=1.3.0
Requires-Dist: transformers
Dynamic: author
Dynamic: author-email
Dynamic: description
Dynamic: description-content-type
Dynamic: requires-dist
Dynamic: summary
